AUTHORS
LICENSE
MANIFEST.in
README.md
distribute_setup.py
setup.py
lxc/__init__.py
pylxc.egg-info/PKG-INFO
pylxc.egg-info/SOURCES.txt
pylxc.egg-info/dependency_links.txt
pylxc.egg-info/top_level.txt
pylxc.egg-info/zip-safe