Metadata-Version: 1.1
Name: pylxc
Version: 0.0.2
Summary: A python wrapper for Linux Containers (LXC)
Home-page: https://github.com/cloud9ers/pylxc
Author: Cloud Niners Ltd.
Author-email: asoliman@cloud9ers.com
License: LGPLv3
Platform: UNKNOWN
Classifier: Development Status :: 5 - Production/Stable
Classifier: Intended Audience :: Developers
Classifier: Intended Audience :: System Administrators
Classifier: License :: OSI Approved :: GNU Library or Lesser General Public License (LGPL)
Classifier: Operating System :: POSIX :: Linux
Classifier: Programming Language :: Python :: 2.7
Classifier: Topic :: System :: Systems Administration
